gpio_manager-3.2.1.dist-info/METADATA
gpio_manager-3.2.1.dist-info/WHEEL
gpio_manager-3.2.1.dist-info/licenses/LICENSE
gpio_manager/__init__.py
gpio_manager/__init__.pyi
gpio_manager/gpio_manager.cpython-311-arm-linux-gnueabihf.so
gpio_manager/py.typed
gpio_manager-3.2.1.dist-info/RECORD
