Metadata-Version: 2.4
Name: gpio_manager
Version: 3.2.1
Classifier: Development Status :: 4 - Beta
Classifier: Programming Language :: Python
Classifier: Programming Language :: Rust
Classifier: Programming Language :: Python :: Implementation :: CPython
Classifier: Programming Language :: Python :: Implementation :: PyPy
License-File: LICENSE
Summary: Rust bindings for the rppal crate to manage GPIO pins on a Raspberry Pi.
Keywords: Raspberry PI 5,Raspberry PI 4,GPIO
Author-email: Rylan Meilutis <rylan.meilutis@gmail.com>
Requires-Python: >=3.8
Project-URL: homepage, https://github.com/Rylan-Meilutis/gpio_manager
Project-URL: documentation, https://gpio-manager.readthedocs.io/en/latest/
Project-URL: repository, https://github.com/Rylan-Meilutis/gpio_manager
